isbnlib_bnf/__init__.py
isbnlib_bnf/_bnf.py
isbnlib_bnf-1.0.3.dist-info/LICENSE-LGPL.txt
isbnlib_bnf-1.0.3.dist-info/METADATA
isbnlib_bnf-1.0.3.dist-info/WHEEL
isbnlib_bnf-1.0.3.dist-info/entry_points.txt
isbnlib_bnf-1.0.3.dist-info/top_level.txt
isbnlib_bnf-1.0.3.dist-info/RECORD
